[
    {
        "Line": "Red",
        "Section": "A",
        "Block Number": 1,
        "Block Length (m)": 50,
        "Block Grade (%)": 0.5,
        "Speed Limit (Km/Hr)": 40,
        "Infrastructure": "",
        "Station Side": "",
        "ELEVATION (M)": 0.25,
        "CUMULATIVE ELEVATION (M)": 0.25
    },
    {
        "Line": "Red",
        "Section": "A",
        "Block Number": 2,
        "Block Length (m)": 50,
        "Block Grade (%)": 1,
        "Speed Limit (Km/Hr)": 40,
        "Infrastructure": "",
        "Station Side": "",
        "ELEVATION (M)": 0.5,
        "CUMULATIVE ELEVATION (M)": 0.75
    },
    {
        "Line": "Red",
        "Section": "A",
        "Block Number": 3,
        "Block Length (m)": 50,
        "Block Grade (%)": 1.5,
        "Speed Limit (Km/Hr)": 40,
        "Infrastructure": "",
        "Station Side": "",
        "ELEVATION (M)": 0.75,
        "CUMULATIVE ELEVATION (M)": 1.5
    },
    {
        "Line": "Red",
        "Section": "B",
        "Block Number": 4,
        "Block Length (m)": 50,
        "Block Grade (%)": 2,
        "Speed Limit (Km/Hr)": 40,
        "Infrastructure": "",
        "Station Side": "",
        "ELEVATION (M)": 1.0,
        "CUMULATIVE ELEVATION (M)": 2.5
    },
    {
        "Line": "Red",
        "Section": "B",
        "Block Number": 5,
        "Block Length (m)": 50,
        "Block Grade (%)": 1.5,
        "Speed Limit (Km/Hr)": 40,
        "Infrastructure": "",
        "Station Side": "",
        "ELEVATION (M)": 0.75,
        "CUMULATIVE ELEVATION (M)": 3.25
    },
    {
        "Line": "Red",
        "Section": "B",
        "Block Number": 6,
        "Block Length (m)": 50,
        "Block Grade (%)": 1,
        "Speed Limit (Km/Hr)": 40,
        "Infrastructure": "",
        "Station Side": "",
        "ELEVATION (M)": 0.5,
        "CUMULATIVE ELEVATION (M)": 3.75
    },
    {
        "Line": "Red",
        "Section": "C",
        "Block Number": 7,
        "Block Length (m)": 75,
        "Block Grade (%)": 0.5,
        "Speed Limit (Km/Hr)": 40,
        "Infrastructure": "STATION: SHADYSIDE",
        "Station Side": "Left/Right",
        "ELEVATION (M)": 0.38,
        "CUMULATIVE ELEVATION (M)": 4.13
    },
    {
        "Line": "Red",
        "Section": "C",
        "Block Number": 8,
        "Block Length (m)": 75,
        "Block Grade (%)": 0,
        "Speed Limit (Km/Hr)": 40,
        "Infrastructure": "",
        "Station Side": "",
        "ELEVATION (M)": 0.0,
        "CUMULATIVE ELEVATION (M)": 4.13
    },
    {
        "Line": "Red",
        "Section": "C",
        "Block Number": 9,
        "Block Length (m)": 75,
        "Block Grade (%)": 0,
        "Speed Limit (Km/Hr)": 40,
        "Infrastructure": "SWITCH TO/FROM YARD (75-yard)",
        "Station Side": "",
        "ELEVATION (M)": 0.0,
        "CUMULATIVE ELEVATION (M)": 4.13
    },
    {
        "Line": "Red",
        "Section": "D",
        "Block Number": 10,
        "Block Length (m)": 75,
        "Block Grade (%)": 0,
        "Speed Limit (Km/Hr)": 40,
        "Infrastructure": "",
        "Station Side": "",
        "ELEVATION (M)": 0.0,
        "CUMULATIVE ELEVATION (M)": 4.13
    },
    {
        "Line": "Red",
        "Section": "D",
        "Block Number": 11,
        "Block Length (m)": 75,
        "Block Grade (%)": -0.5,
        "Speed Limit (Km/Hr)": 40,
        "Infrastructure": "RAILWAY CROSSING",
        "Station Side": "",
        "ELEVATION (M)": -0.38,
        "CUMULATIVE ELEVATION (M)": 3.75
    },
    {
        "Line": "Red",
        "Section": "D",
        "Block Number": 12,
        "Block Length (m)": 75,
        "Block Grade (%)": -1,
        "Speed Limit (Km/Hr)": 40,
        "Infrastructure": "",
        "Station Side": "",
        "ELEVATION (M)": -0.75,
        "CUMULATIVE ELEVATION (M)": 3.0
    },
    {
        "Line": "Red",
        "Section": "E",
        "Block Number": 13,
        "Block Length (m)": 70,
        "Block Grade (%)": -2,
        "Speed Limit (Km/Hr)": 40,
        "Infrastructure": "",
        "Station Side": "",
        "ELEVATION (M)": -1.4,
        "CUMULATIVE ELEVATION (M)": 1.6
    },
    {
        "Line": "Red",
        "Section": "E",
        "Block Number": 14,
        "Block Length (m)": 60,
        "Block Grade (%)": -1.25,
        "Speed Limit (Km/Hr)": 40,
        "Infrastructure": "",
        "Station Side": "",
        "ELEVATION (M)": -0.75,
        "CUMULATIVE ELEVATION (M)": 0.85
    },
    {
        "Line": "Red",
        "Section": "E",
        "Block Number": 15,
        "Block Length (m)": 60,
        "Block Grade (%)": -1,
        "Speed Limit (Km/Hr)": 40,
        "Infrastructure": "SWITCH (15-16; 1-16)",
        "Station Side": "",
        "ELEVATION (M)": -0.6,
        "CUMULATIVE ELEVATION (M)": 0.25
    },
    {
        "Line": "Red",
        "Section": "F",
        "Block Number": 16,
        "Block Length (m)": 50,
        "Block Grade (%)": -0.5,
        "Speed Limit (Km/Hr)": 40,
        "Infrastructure": "STATION: HERRON AVE",
        "Station Side": "Left/Right",
        "ELEVATION (M)": -0.25,
        "CUMULATIVE ELEVATION (M)": 0.0
    },
    {
        "Line": "Red",
        "Section": "F",
        "Block Number": 17,
        "Block Length (m)": 200,
        "Block Grade (%)": -0.5,
        "Speed Limit (Km/Hr)": 55,
        "Infrastructure": "",
        "Station Side": "",
        "ELEVATION (M)": -1.0,
        "CUMULATIVE ELEVATION (M)": -1.0
    },
    {
        "Line": "Red",
        "Section": "F",
        "Block Number": 18,
        "Block Length (m)": 400,
        "Block Grade (%)": -0.06025,
        "Speed Limit (Km/Hr)": 70,
        "Infrastructure": "",
        "Station Side": "",
        "ELEVATION (M)": -0.24,
        "CUMULATIVE ELEVATION (M)": -1.24
    },
    {
        "Line": "Red",
        "Section": "F",
        "Block Number": 19,
        "Block Length (m)": 400,
        "Block Grade (%)": 0,
        "Speed Limit (Km/Hr)": 70,
        "Infrastructure": "",
        "Station Side": "",
        "ELEVATION (M)": 0.0,
        "CUMULATIVE ELEVATION (M)": -1.24
    },
    {
        "Line": "Red",
        "Section": "F",
        "Block Number": 20,
        "Block Length (m)": 200,
        "Block Grade (%)": 0,
        "Speed Limit (Km/Hr)": 70,
        "Infrastructure": "",
        "Station Side": "",
        "ELEVATION (M)": 0.0,
        "CUMULATIVE ELEVATION (M)": -1.24
    },
    {
        "Line": "Red",
        "Section": "G",
        "Block Number": 21,
        "Block Length (m)": 100,
        "Block Grade (%)": 0,
        "Speed Limit (Km/Hr)": 55,
        "Infrastructure": "STATION; SWISSVILLE",
        "Station Side": "Left/Right",
        "ELEVATION (M)": 0.0,
        "CUMULATIVE ELEVATION (M)": -1.24
    },
    {
        "Line": "Red",
        "Section": "G",
        "Block Number": 22,
        "Block Length (m)": 100,
        "Block Grade (%)": 0,
        "Speed Limit (Km/Hr)": 55,
        "Infrastructure": "",
        "Station Side": "",
        "ELEVATION (M)": 0.0,
        "CUMULATIVE ELEVATION (M)": -1.24
    },
    {
        "Line": "Red",
        "Section": "G",
        "Block Number": 23,
        "Block Length (m)": 100,
        "Block Grade (%)": 0,
        "Speed Limit (Km/Hr)": 55,
        "Infrastructure": "",
        "Station Side": "",
        "ELEVATION (M)": 0.0,
        "CUMULATIVE ELEVATION (M)": -1.24
    },
    {
        "Line": "Red",
        "Section": "H",
        "Block Number": 24,
        "Block Length (m)": 100,
        "Block Grade (%)": 0,
        "Speed Limit (Km/Hr)": 55,
        "Infrastructure": "",
        "Station Side": "",
        "ELEVATION (M)": 0.0,
        "CUMULATIVE ELEVATION (M)": -1.24
    },
    {
        "Line": "Red",
        "Section": "H",
        "Block Number": 25,
        "Block Length (m)": 100,
        "Block Grade (%)": 0.5,
        "Speed Limit (Km/Hr)": 55,
        "Infrastructure": "SWITCH (25-26)",
        "Station Side": "",
        "ELEVATION (M)": 0.5,
        "CUMULATIVE ELEVATION (M)": -0.74
    },
    {
        "Line": "Red",
        "Section": "H",
        "Block Number": 26,
        "Block Length (m)": 150,
        "Block Grade (%)": 0,
        "Speed Limit (Km/Hr)": 55,
        "Infrastructure": "UNDERGROUND",
        "Station Side": "",
        "ELEVATION (M)": 0.0,
        "CUMULATIVE ELEVATION (M)": -0.74
    },
    {
        "Line": "Red",
        "Section": "H",
        "Block Number": 27,
        "Block Length (m)": 150,
        "Block Grade (%)": 0,
        "Speed Limit (Km/Hr)": 55,
        "Infrastructure": "UNDERGROUND",
        "Station Side": "",
        "ELEVATION (M)": 0.0,
        "CUMULATIVE ELEVATION (M)": -0.74
    },
    {
        "Line": "Red",
        "Section": "H",
        "Block Number": 28,
        "Block Length (m)": 150,
        "Block Grade (%)": 0.5,
        "Speed Limit (Km/Hr)": 55,
        "Infrastructure": "",
        "Station Side": "",
        "ELEVATION (M)": 0.75,
        "CUMULATIVE ELEVATION (M)": 0.01
    },
    {
        "Line": "Red",
        "Section": "H",
        "Block Number": 29,
        "Block Length (m)": 150,
        "Block Grade (%)": 0.5,
        "Speed Limit (Km/Hr)": 55,
        "Infrastructure": "STATION: HAZELWOOD",
        "Station Side": "Left",
        "ELEVATION (M)": 0.75,
        "CUMULATIVE ELEVATION (M)": 0.76
    },
    {
        "Line": "Red",
        "Section": "H",
        "Block Number": 30,
        "Block Length (m)": 200,
        "Block Grade (%)": -1,
        "Speed Limit (Km/Hr)": 55,
        "Infrastructure": "",
        "Station Side": "",
        "ELEVATION (M)": -2.0,
        "CUMULATIVE ELEVATION (M)": -1.24
    },
    {
        "Line": "Red",
        "Section": "H",
        "Block Number": 31,
        "Block Length (m)": 200,
        "Block Grade (%)": -0.5,
        "Speed Limit (Km/Hr)": 55,
        "Infrastructure": "",
        "Station Side": "",
        "ELEVATION (M)": -1.0,
        "CUMULATIVE ELEVATION (M)": -2.24
    },
    {
        "Line": "Red",
        "Section": "H",
        "Block Number": 32,
        "Block Length (m)": 200,
        "Block Grade (%)": -1.5,
        "Speed Limit (Km/Hr)": 55,
        "Infrastructure": "",
        "Station Side": "",
        "ELEVATION (M)": -3.0,
        "CUMULATIVE ELEVATION (M)": -5.24
    },
    {
        "Line": "Red",
        "Section": "H",
        "Block Number": 33,
        "Block Length (m)": 200,
        "Block Grade (%)": -1,
        "Speed Limit (Km/Hr)": 55,
        "Infrastructure": "",
        "Station Side": "",
        "ELEVATION (M)": -2.0,
        "CUMULATIVE ELEVATION (M)": -7.24
    },
    {
        "Line": "Red",
        "Section": "H",
        "Block Number": 34,
        "Block Length (m)": 200,
        "Block Grade (%)": 0,
        "Speed Limit (Km/Hr)": 55,
        "Infrastructure": "SWITCH (33-34)",
        "Station Side": "",
        "ELEVATION (M)": 0.0,
        "CUMULATIVE ELEVATION (M)": -7.24
    },
    {
        "Line": "Red",
        "Section": "H",
        "Block Number": 35,
        "Block Length (m)": 200,
        "Block Grade (%)": 1,
        "Speed Limit (Km/Hr)": 55,
        "Infrastructure": "STATION: CRAFTON",
        "Station Side": "Right",
        "ELEVATION (M)": 2.0,
        "CUMULATIVE ELEVATION (M)": -5.24
    },
    {
        "Line": "Red",
        "Section": "H",
        "Block Number": 36,
        "Block Length (m)": 150,
        "Block Grade (%)": 1.5,
        "Speed Limit (Km/Hr)": 55,
        "Infrastructure": "",
        "Station Side": "",
        "ELEVATION (M)": 2.25,
        "CUMULATIVE ELEVATION (M)": -3.0
    },
    {
        "Line": "Red",
        "Section": "H",
        "Block Number": 37,
        "Block Length (m)": 150,
        "Block Grade (%)": 1,
        "Speed Limit (Km/Hr)": 55,
        "Infrastructure": "",
        "Station Side": "",
        "ELEVATION (M)": 1.5,
        "CUMULATIVE ELEVATION (M)": -1.5
    },
    {
        "Line": "Red",
        "Section": "H",
        "Block Number": 38,
        "Block Length (m)": 150,
        "Block Grade (%)": 0.5,
        "Speed Limit (Km/Hr)": 55,
        "Infrastructure": "BRIDGE",
        "Station Side": "",
        "ELEVATION (M)": 0.75,
        "CUMULATIVE ELEVATION (M)": -0.75
    },
    {
        "Line": "Red",
        "Section": "H",
        "Block Number": 39,
        "Block Length (m)": 150,
        "Block Grade (%)": 0,
        "Speed Limit (Km/Hr)": 55,
        "Infrastructure": "BRIDGE",
        "Station Side": "",
        "ELEVATION (M)": 0.0,
        "CUMULATIVE ELEVATION (M)": -0.75
    },
    {
        "Line": "Red",
        "Section": "H",
        "Block Number": 40,
        "Block Length (m)": 150,
        "Block Grade (%)": 0.5,
        "Speed Limit (Km/Hr)": 70,
        "Infrastructure": "",
        "Station Side": "",
        "ELEVATION (M)": 0.75,
        "CUMULATIVE ELEVATION (M)": 0.0
    },
    {
        "Line": "Red",
        "Section": "H",
        "Block Number": 41,
        "Block Length (m)": 150,
        "Block Grade (%)": 1,
        "Speed Limit (Km/Hr)": 70,
        "Infrastructure": "",
        "Station Side": "",
        "ELEVATION (M)": 1.5,
        "CUMULATIVE ELEVATION (M)": 1.5
    },
    {
        "Line": "Red",
        "Section": "H",
        "Block Number": 42,
        "Block Length (m)": 150,
        "Block Grade (%)": 1.5,
        "Speed Limit (Km/Hr)": 70,
        "Infrastructure": "",
        "Station Side": "",
        "ELEVATION (M)": 2.25,
        "CUMULATIVE ELEVATION (M)": 3.75
    },
    {
        "Line": "Red",
        "Section": "H",
        "Block Number": 43,
        "Block Length (m)": 150,
        "Block Grade (%)": 0.5,
        "Speed Limit (Km/Hr)": 70,
        "Infrastructure": "STATION: WINDRIDGE",
        "Station Side": "Left/Right",
        "ELEVATION (M)": 0.75,
        "CUMULATIVE ELEVATION (M)": 4.5
    },
    {
        "Line": "Red",
        "Section": "H",
        "Block Number": 44,
        "Block Length (m)": 100,
        "Block Grade (%)": 1.5,
        "Speed Limit (Km/Hr)": 70,
        "Infrastructure": "TUNNEL",
        "Station Side": "",
        "ELEVATION (M)": 1.5,
        "CUMULATIVE ELEVATION (M)": 6.0
    },
    {
        "Line": "Red",
        "Section": "H",
        "Block Number": 45,
        "Block Length (m)": 100,
        "Block Grade (%)": 2,
        "Speed Limit (Km/Hr)": 70,
        "Infrastructure": "TUNNEL",
        "Station Side": "",
        "ELEVATION (M)": 2.0,
        "CUMULATIVE ELEVATION (M)": 8.0
    },
    {
        "Line": "Red",
        "Section": "I",
        "Block Number": 46,
        "Block Length (m)": 100,
        "Block Grade (%)": 2,
        "Speed Limit (Km/Hr)": 70,
        "Infrastructure": "TUNNEL",
        "Station Side": "",
        "ELEVATION (M)": 2.0,
        "CUMULATIVE ELEVATION (M)": 10.0
    },
    {
        "Line": "Red",
        "Section": "I",
        "Block Number": 47,
        "Block Length (m)": 100,
        "Block Grade (%)": 0.5,
        "Speed Limit (Km/Hr)": 70,
        "Infrastructure": "TUNNEL",
        "Station Side": "",
        "ELEVATION (M)": 0.5,
        "CUMULATIVE ELEVATION (M)": 10.5
    },
    {
        "Line": "Red",
        "Section": "I",
        "Block Number": 48,
        "Block Length (m)": 200,
        "Block Grade (%)": 1,
        "Speed Limit (Km/Hr)": 70,
        "Infrastructure": "",
        "Station Side": "",
        "ELEVATION (M)": 2.0,
        "CUMULATIVE ELEVATION (M)": 12.5
    },
    {
        "Line": "Red",
        "Section": "J",
        "Block Number": 49,
        "Block Length (m)": 200,
        "Block Grade (%)": 1.5,
        "Speed Limit (Km/Hr)": 70,
        "Infrastructure": "",
        "Station Side": "",
        "ELEVATION (M)": 3.0,
        "CUMULATIVE ELEVATION (M)": 15.5
    },
    {
        "Line": "Red",
        "Section": "J",
        "Block Number": 50,
        "Block Length (m)": 200,
        "Block Grade (%)": 2,
        "Speed Limit (Km/Hr)": 70,
        "Infrastructure": "",
        "Station Side": "",
        "ELEVATION (M)": 4.0,
        "CUMULATIVE ELEVATION (M)": 19.5
    },
    {
        "Line": "Red",
        "Section": "J",
        "Block Number": 51,
        "Block Length (m)": 200,
        "Block Grade (%)": 2.5,
        "Speed Limit (Km/Hr)": 70,
        "Infrastructure": "",
        "Station Side": "",
        "ELEVATION (M)": 5.0,
        "CUMULATIVE ELEVATION (M)": 24.5
    },
    {
        "Line": "Red",
        "Section": "J",
        "Block Number": 52,
        "Block Length (m)": 200,
        "Block Grade (%)": 2,
        "Speed Limit (Km/Hr)": 70,
        "Infrastructure": "",
        "Station Side": "",
        "ELEVATION (M)": 4.0,
        "CUMULATIVE ELEVATION (M)": 28.5
    },
    {
        "Line": "Red",
        "Section": "J",
        "Block Number": 53,
        "Block Length (m)": 200,
        "Block Grade (%)": 1.5,
        "Speed Limit (Km/Hr)": 70,
        "Infrastructure": "",
        "Station Side": "",
        "ELEVATION (M)": 3.0,
        "CUMULATIVE ELEVATION (M)": 31.5
    },
    {
        "Line": "Red",
        "Section": "J",
        "Block Number": 54,
        "Block Length (m)": 200,
        "Block Grade (%)": 1,
        "Speed Limit (Km/Hr)": 70,
        "Infrastructure": "",
        "Station Side": "",
        "ELEVATION (M)": 2.0,
        "CUMULATIVE ELEVATION (M)": 33.5
    },
    {
        "Line": "Red",
        "Section": "K",
        "Block Number": 55,
        "Block Length (m)": 200,
        "Block Grade (%)": 0.5,
        "Speed Limit (Km/Hr)": 70,
        "Infrastructure": "BRIDGE",
        "Station Side": "",
        "ELEVATION (M)": 1.0,
        "CUMULATIVE ELEVATION (M)": 34.5
    },
    {
        "Line": "Red",
        "Section": "K",
        "Block Number": 56,
        "Block Length (m)": 100,
        "Block Grade (%)": 0,
        "Speed Limit (Km/Hr)": 70,
        "Infrastructure": "BRIDGE",
        "Station Side": "",
        "ELEVATION (M)": 0.0,
        "CUMULATIVE ELEVATION (M)": 34.5
    },
    {
        "Line": "Red",
        "Section": "K",
        "Block Number": 57,
        "Block Length (m)": 100,
        "Block Grade (%)": -0.5,
        "Speed Limit (Km/Hr)": 70,
        "Infrastructure": "BRIDGE",
        "Station Side": "",
        "ELEVATION (M)": -0.5,
        "CUMULATIVE ELEVATION (M)": 34.0
    },
    {
        "Line": "Red",
        "Section": "L",
        "Block Number": 58,
        "Block Length (m)": 100,
        "Block Grade (%)": -1,
        "Speed Limit (Km/Hr)": 70,
        "Infrastructure": "",
        "Station Side": "",
        "ELEVATION (M)": -1.0,
        "CUMULATIVE ELEVATION (M)": 33.0
    },
    {
        "Line": "Red",
        "Section": "L",
        "Block Number": 59,
        "Block Length (m)": 100,
        "Block Grade (%)": -1.5,
        "Speed Limit (Km/Hr)": 70,
        "Infrastructure": "",
        "Station Side": "",
        "ELEVATION (M)": -1.5,
        "CUMULATIVE ELEVATION (M)": 31.5
    },
    {
        "Line": "Red",
        "Section": "L",
        "Block Number": 60,
        "Block Length (m)": 150,
        "Block Grade (%)": -2,
        "Speed Limit (Km/Hr)": 70,
        "Infrastructure": "",
        "Station Side": "",
        "ELEVATION (M)": -3.0,
        "CUMULATIVE ELEVATION (M)": 28.5
    },
    {
        "Line": "Red",
        "Section": "M",
        "Block Number": 61,
        "Block Length (m)": 150,
        "Block Grade (%)": -2.5,
        "Speed Limit (Km/Hr)": 70,
        "Infrastructure": "",
        "Station Side": "",
        "ELEVATION (M)": -3.75,
        "CUMULATIVE ELEVATION (M)": 24.75
    },
    {
        "Line": "Red",
        "Section": "M",
        "Block Number": 62,
        "Block Length (m)": 150,
        "Block Grade (%)": -3,
        "Speed Limit (Km/Hr)": 70,
        "Infrastructure": "",
        "Station Side": "",
        "ELEVATION (M)": -4.5,
        "CUMULATIVE ELEVATION (M)": 20.25
    },
    {
        "Line": "Red",
        "Section": "M",
        "Block Number": 63,
        "Block Length (m)": 150,
        "Block Grade (%)": -2,
        "Speed Limit (Km/Hr)": 70,
        "Infrastructure": "STATION: SHERIDAN",
        "Station Side": "Right",
        "ELEVATION (M)": -3.0,
        "CUMULATIVE ELEVATION (M)": 17.25
    },
    {
        "Line": "Red",
        "Section": "N",
        "Block Number": 64,
        "Block Length (m)": 200,
        "Block Grade (%)": -1.5,
        "Speed Limit (Km/Hr)": 70,
        "Infrastructure": "",
        "Station Side": "",
        "ELEVATION (M)": -3.0,
        "CUMULATIVE ELEVATION (M)": 14.25
    },
    {
        "Line": "Red",
        "Section": "N",
        "Block Number": 65,
        "Block Length (m)": 200,
        "Block Grade (%)": -1,
        "Speed Limit (Km/Hr)": 70,
        "Infrastructure": "",
        "Station Side": "",
        "ELEVATION (M)": -2.0,
        "CUMULATIVE ELEVATION (M)": 12.25
    },
    {
        "Line": "Red",
        "Section": "N",
        "Block Number": 66,
        "Block Length (m)": 200,
        "Block Grade (%)": -0.5,
        "Speed Limit (Km/Hr)": 70,
        "Infrastructure": "",
        "Station Side": "",
        "ELEVATION (M)": -1.0,
        "CUMULATIVE ELEVATION (M)": 11.25
    },
    {
        "Line": "Red",
        "Section": "O",
        "Block Number": 67,
        "Block Length (m)": 200,
        "Block Grade (%)": 0,
        "Speed Limit (Km/Hr)": 70,
        "Infrastructure": "SWITCH (66-67)",
        "Station Side": "",
        "ELEVATION (M)": 0.0,
        "CUMULATIVE ELEVATION (M)": 11.25
    },
    {
        "Line": "Red",
        "Section": "P",
        "Block Number": 68,
        "Block Length (m)": 200,
        "Block Grade (%)": 1,
        "Speed Limit (Km/Hr)": 70,
        "Infrastructure": "",
        "Station Side": "",
        "ELEVATION (M)": 2.0,
        "CUMULATIVE ELEVATION (M)": 13.25
    },
    {
        "Line": "Red",
        "Section": "P",
        "Block Number": 69,
        "Block Length (m)": 200,
        "Block Grade (%)": 1.5,
        "Speed Limit (Km/Hr)": 70,
        "Infrastructure": "BRIDGE",
        "Station Side": "",
        "ELEVATION (M)": 3.0,
        "CUMULATIVE ELEVATION (M)": 16.25
    },
    {
        "Line": "Red",
        "Section": "P",
        "Block Number": 70,
        "Block Length (m)": 200,
        "Block Grade (%)": 2,
        "Speed Limit (Km/Hr)": 70,
        "Infrastructure": "BRIDGE",
        "Station Side": "",
        "ELEVATION (M)": 4.0,
        "CUMULATIVE ELEVATION (M)": 20.25
    },
    {
        "Line": "Red",
        "Section": "Q",
        "Block Number": 71,
        "Block Length (m)": 150,
        "Block Grade (%)": 2,
        "Speed Limit (Km/Hr)": 70,
        "Infrastructure": "",
        "Station Side": "",
        "ELEVATION (M)": 3.0,
        "CUMULATIVE ELEVATION (M)": 23.25
    },
    {
        "Line": "Red",
        "Section": "R",
        "Block Number": 72,
        "Block Length (m)": 150,
        "Block Grade (%)": 1.5,
        "Speed Limit (Km/Hr)": 70,
        "Infrastructure": "",
        "Station Side": "",
        "ELEVATION (M)": 2.25,
        "CUMULATIVE ELEVATION (M)": 25.5
    },
    {
        "Line": "Red",
        "Section": "S",
        "Block Number": 73,
        "Block Length (m)": 150,
        "Block Grade (%)": 1,
        "Speed Limit (Km/Hr)": 70,
        "Infrastructure": "STATION: FOREST GLEN",
        "Station Side": "Right",
        "ELEVATION (M)": 1.5,
        "CUMULATIVE ELEVATION (M)": 27.0
    },
    {
        "Line": "Red",
        "Section": "S",
        "Block Number": 74,
        "Block Length (m)": 150,
        "Block Grade (%)": 0.5,
        "Speed Limit (Km/Hr)": 70,
        "Infrastructure": "",
        "Station Side": "",
        "ELEVATION (M)": 0.75,
        "CUMULATIVE ELEVATION (M)": 27.75
    },
    {
        "Line": "Red",
        "Section": "S",
        "Block Number": 75,
        "Block Length (m)": 150,
        "Block Grade (%)": 0,
        "Speed Limit (Km/Hr)": 70,
        "Infrastructure": "",
        "Station Side": "",
        "ELEVATION (M)": 0.0,
        "CUMULATIVE ELEVATION (M)": 27.75
    },
    {
        "Line": "Red",
        "Section": "T",
        "Block Number": 76,
        "Block Length (m)": 150,
        "Block Grade (%)": -0.5,
        "Speed Limit (Km/Hr)": 70,
        "Infrastructure": "SWITCH (75-76)",
        "Station Side": "",
        "ELEVATION (M)": -0.75,
        "CUMULATIVE ELEVATION (M)": 27.0
    }

]
